{"name":"build-javascript","namedChunkGroups":{"polyfill":{"name":"polyfill","assets":[{"name":"webpack-runtime-afec1ab39cce71a33c84.js","size":3688},{"name":"polyfill-5c61d966f81031d25db0.js","size":85826}],"filteredAssets":0,"assetsSize":89514,"filteredAuxiliaryAssets":2,"auxiliaryAssetsSize":223184},"app":{"name":"app","assets":[{"name":"webpack-runtime-afec1ab39cce71a33c84.js","size":3688},{"name":"framework-83134f0e02da31458b92.js","size":141190},{"name":"app-c9f927dadf50310a91a2.js","size":136035}],"filteredAssets":0,"assetsSize":280913,"filteredAuxiliaryAssets":3,"auxiliaryAssetsSize":982571},"component---src-pages-404-js":{"name":"component---src-pages-404-js","assets":[{"name":"component---src-pages-404-js-286090a139000f04c38a.js","size":795}],"filteredAssets":0,"assetsSize":795,"filteredAuxiliaryAssets":1,"auxiliaryAssetsSize":2025},"component---src-pages-index-js":{"name":"component---src-pages-index-js","assets":[{"name":"component---src-pages-index-js-6118928f8b99f7c9763a.js","size":1251614}],"filteredAssets":0,"assetsSize":1251614,"filteredAuxiliaryAssets":1,"auxiliaryAssetsSize":3171447}},"assetsByChunkName":{"polyfill":["webpack-runtime-afec1ab39cce71a33c84.js","polyfill-5c61d966f81031d25db0.js"],"app":["webpack-runtime-afec1ab39cce71a33c84.js","framework-83134f0e02da31458b92.js","app-c9f927dadf50310a91a2.js"],"component---src-pages-404-js":["component---src-pages-404-js-286090a139000f04c38a.js"],"component---src-pages-index-js":["component---src-pages-index-js-6118928f8b99f7c9763a.js"]},"childAssetsByChunkName":{}}